ivisit/__init__.py
ivisit/defdb.py
ivisit/defdialogs.py
ivisit/help.py
ivisit/matplotlib.py
ivisit/parser.py
ivisit/simulation.py
ivisit/special.py
ivisit/widgetdefcollection.py
ivisit/widgets.py
ivisit-0.71.dist-info/LICENSE
ivisit-0.71.dist-info/METADATA
ivisit-0.71.dist-info/WHEEL
ivisit-0.71.dist-info/top_level.txt
ivisit-0.71.dist-info/RECORD
