Metadata-Version: 2.1
Name: ivisit
Version: 0.71
Summary: Interactive VIsual SImulation Tool
Home-page: https://github.com/aknoblauch/ivisit
Author: Andreas Knoblauch
Author-email: knoblauch@hs-albsig.de
License: UNKNOWN
Project-URL: Bug Tracker, https://github.com/aknoblauch/ivisit/issues
Platform: UNKNOWN
Classifier: Programming Language :: Python :: 3
Classifier: License :: OSI Approved :: MIT License
Classifier: Operating System :: OS Independent
Requires-Python: >=3.6
License-File: LICENSE
